{"data": {"ethereum": {"smartContractCalls": [{"smartContractMethod": {"name": "ArbenisActive", "signature": "ArbenisActive()", "signatureHash": "2151eddc"}, "caller": {"address": "0x21ba4bbeb3fd69c9cc65975659d22b96726f9ca1"}, "success": true, "count": 1}, {"smartContractMethod": {"name": "ArbenisActive", "signature": "ArbenisActive()", "signatureHash": "2151eddc"}, "caller": {"address": "0x9acf67684198969687ecadf2d9351981bf6f33b2"}, "success": true, "count": 1}, {"smartContractMethod": {"name": "Contract Creation", "signature": null, "signatureHash": "60606040"}, "caller": {"address": "0x9acf67684198969687ecadf2d9351981bf6f33b2"}, "success": true, "count": 1}, {"smartContractMethod": {"name": "buy", "signature": "buy(address)", "signatureHash": "f088d547"}, "caller": {"address": "0x0a3af58cd040f91bb4ba3c10c1a856884664b952"}, "success": true, "count": 16}, {"smartContractMethod": {"name": "buy", "signature": "buy(address)", "signatureHash": "f088d547"}, "caller": {"address": "0x1e6abd6580ce25799ab0b7b1bc69455d13674aaf"}, "success": true, "count": 16}, {"smartContractMethod": {"name": "buy", "signature": "buy(address)", "signatureHash": "f088d547"}, "caller": {"address": "0x24992541287d344b3ee610b6ec7f4cde01e8a784"}, "success": true, "count": 1}, {"smartContractMethod": {"name": "buy", "signature": "buy(address)", "signatureHash": "f088d547"}, "caller": {"address": "0x2503425d6f84c32795384e3ee8186d05fdd13ec4"}, "success": true, "count": 2}, {"smartContractMethod": {"name": "buy", "signature": "buy(address)", "signatureHash": "f088d547"}, "caller": {"address": "0x2800a6d8fd79c4012c90ae3c07358a865e71fe1d"}, "success": true, "count": 1}, {"smartContractMethod": {"name": "buy", "signature": "buy(address)", "signatureHash": "f088d547"}, "caller": {"address": "0x29249b2745a9443d1243261e30e3571f055f7297"}, "success": true, "count": 16}, {"smartContractMethod": {"name": "buy", "signature": "buy(address)", "signatureHash": "f088d547"}, "caller": {"address": "0x2e7f1881a3719200ce268f56fe42710987201fc4"}, "success": true, "count": 1}, {"smartContractMethod": {"name": "buy", "signature": "buy(address)", "signatureHash": "f088d547"}, "caller": {"address": "0x353189c3780c31b954efe64e4f53cf3d1aba00f1"}, "success": true, "count": 2}, {"smartContractMethod": {"name": "buy", "signature": "buy(address)", "signatureHash": "f088d547"}, "caller": {"address": "0x36e058332ae39efad2315776b9c844e30d07388b"}, "success": true, "count": 1}, {"smartContractMethod": {"name": "buy", "signature": "buy(address)", "signatureHash": "f088d547"}, "caller": {"address": "0x409e494dc9d602197af25e201f8b7c3813455a1c"}, "success": true, "count": 2}, {"smartContractMethod": {"name": "buy", "signature": "buy(address)", "signatureHash": "f088d547"}, "caller": {"address": "0x5479a9ec6386db424b563ef059fc127042543a5d"}, "success": true, "count": 1}, {"smartContractMethod": {"name": "buy", "signature": "buy(address)", "signatureHash": "f088d547"}, "caller": {"address": "0x5aa8ceecbdd7d87106fdd8c333af0195aacad89b"}, "success": true, "count": 1}, {"smartContractMethod": {"name": "buy", "signature": "buy(address)", "signatureHash": "f088d547"}, "caller": {"address": "0x5c25a5bf9478b6c20a9da2117433400a490bf304"}, "success": true, "count": 10}, {"smartContractMethod": {"name": "buy", "signature": "buy(address)", "signatureHash": "f088d547"}, "caller": {"address": "0x701a80fc33e06981954b468641bfd1c9c386ff2f"}, "success": true, "count": 16}, {"smartContractMethod": {"name": "buy", "signature": "buy(address)", "signatureHash": "f088d547"}, "caller": {"address": "0x8ef2c0bad8ad2f6508436f7bf2684b15fcc14601"}, "success": true, "count": 1}, {"smartContractMethod": {"name": "buy", "signature": "buy(address)", "signatureHash": "f088d547"}, "caller": {"address": "0x952d549f4e069930f74a8d51d74f515c0e0e8a66"}, "success": true, "count": 16}, {"smartContractMethod": {"name": "buy", "signature": "buy(address)", "signatureHash": "f088d547"}, "caller": {"address": "0x984ebf6a71a946facc40f4bcbdfa50ac8edc3fbf"}, "success": true, "count": 12}, {"smartContractMethod": {"name": "buy", "signature": "buy(address)", "signatureHash": "f088d547"}, "caller": {"address": "0x9acf67684198969687ecadf2d9351981bf6f33b2"}, "success": true, "count": 1}, {"smartContractMethod": {"name": "buy", "signature": "buy(address)", "signatureHash": "f088d547"}, "caller": {"address": "0xaa772f39c138b8e77424c17c9d6556e959545236"}, "success": true, "count": 16}, {"smartContractMethod": {"name": "buy", "signature": "buy(address)", "signatureHash": "f088d547"}, "caller": {"address": "0xaa9b264f2e3a8569617d557884f2fa4b6da5ac98"}, "success": true, "count": 16}, {"smartContractMethod": {"name": "buy", "signature": "buy(address)", "signatureHash": "f088d547"}, "caller": {"address": "0xaffe9c89a700270c16950ad02a253f3ab49ced64"}, "success": true, "count": 1}, {"smartContractMethod": {"name": "buy", "signature": "buy(address)", "signatureHash": "f088d547"}, "caller": {"address": "0xb58c2638e6499e472c217644054f4e6ca828f44a"}, "success": true, "count": 16}, {"smartContractMethod": {"name": "buy", "signature": "buy(address)", "signatureHash": "f088d547"}, "caller": {"address": "0xb74d5f0a81ce99ac1857133e489bc2b4954935ff"}, "success": false, "count": 5}, {"smartContractMethod": {"name": "buy", "signature": "buy(address)", "signatureHash": "f088d547"}, "caller": {"address": "0xb74d5f0a81ce99ac1857133e489bc2b4954935ff"}, "success": true, "count": 1}, {"smartContractMethod": {"name": "buy", "signature": "buy(address)", "signatureHash": "f088d547"}, "caller": {"address": "0xb78a154c864af73906d2e9c1edcc0c9c642ecee9"}, "success": true, "count": 17}, {"smartContractMethod": {"name": "buy", "signature": "buy(address)", "signatureHash": "f088d547"}, "caller": {"address": "0xc01d702276235988b178081b48cb754a7e5ba7ac"}, "success": true, "count": 16}, {"smartContractMethod": {"name": "buy", "signature": "buy(address)", "signatureHash": "f088d547"}, "caller": {"address": "0xd69a792e1a5da2efdf5c9c09d495255311399fdd"}, "success": true, "count": 16}, {"smartContractMethod": {"name": "buy", "signature": "buy(address)", "signatureHash": "f088d547"}, "caller": {"address": "0xd76c1a10de38d17d872162c1a2c599b1a9a82cb9"}, "success": true, "count": 16}, {"smartContractMethod": {"name": "buy", "signature": "buy(address)", "signatureHash": "f088d547"}, "caller": {"address": "0xd7fcf5bdaf521a39c883dc6d72b9ec941b272f9b"}, "success": true, "count": 16}, {"smartContractMethod": {"name": "buy", "signature": "buy(address)", "signatureHash": "f088d547"}, "caller": {"address": "0xe012157d741d568d5f14ddc6bbb724e9132ca86d"}, "success": true, "count": 1}, {"smartContractMethod": {"name": "buy", "signature": "buy(address)", "signatureHash": "f088d547"}, "caller": {"address": "0xe6bb53b3a2e8fc73c0431f9efa51c8dbc4706409"}, "success": true, "count": 4}, {"smartContractMethod": {"name": "buy", "signature": "buy(address)", "signatureHash": "f088d547"}, "caller": {"address": "0xed108484fd3681e24a11fa1ac601249b138877fd"}, "success": true, "count": 1}, {"smartContractMethod": {"name": "buy", "signature": "buy(address)", "signatureHash": "f088d547"}, "caller": {"address": "0xef02ff526caa15c74579f9bd9f65c3747fc1dbe8"}, "success": true, "count": 16}, {"smartContractMethod": {"name": "buy", "signature": "buy(address)", "signatureHash": "f088d547"}, "caller": {"address": "0xef89bf2ab0f4cafd96b8b09423315b4b022ce1be"}, "success": true, "count": 2}, {"smartContractMethod": {"name": "disableInitialStage", "signature": "disableInitialStage()", "signatureHash": "a8e04f34"}, "caller": {"address": "0x9acf67684198969687ecadf2d9351981bf6f33b2"}, "success": true, "count": 1}, {"smartContractMethod": {"name": "exit", "signature": "exit()", "signatureHash": "e9fad8ee"}, "caller": {"address": "0x52f2cc12b89a3fb4d4f2230487297fd402e6a711"}, "success": true, "count": 1}, {"smartContractMethod": {"name": "exit", "signature": "exit()", "signatureHash": "e9fad8ee"}, "caller": {"address": "0xb74d5f0a81ce99ac1857133e489bc2b4954935ff"}, "success": true, "count": 1}, {"smartContractMethod": {"name": "reinvest", "signature": "reinvest()", "signatureHash": "fdb5a03e"}, "caller": {"address": "0x24992541287d344b3ee610b6ec7f4cde01e8a784"}, "success": true, "count": 1}, {"smartContractMethod": {"name": "reinvest", "signature": "reinvest()", "signatureHash": "fdb5a03e"}, "caller": {"address": "0x409e494dc9d602197af25e201f8b7c3813455a1c"}, "success": false, "count": 1}, {"smartContractMethod": {"name": "reinvest", "signature": "reinvest()", "signatureHash": "fdb5a03e"}, "caller": {"address": "0x409e494dc9d602197af25e201f8b7c3813455a1c"}, "success": true, "count": 3}, {"smartContractMethod": {"name": "reinvest", "signature": "reinvest()", "signatureHash": "fdb5a03e"}, "caller": {"address": "0x9acf67684198969687ecadf2d9351981bf6f33b2"}, "success": true, "count": 1}, {"smartContractMethod": {"name": "reinvest", "signature": "reinvest()", "signatureHash": "fdb5a03e"}, "caller": {"address": "0xe012157d741d568d5f14ddc6bbb724e9132ca86d"}, "success": true, "count": 1}, {"smartContractMethod": {"name": "reinvest", "signature": "reinvest()", "signatureHash": "fdb5a03e"}, "caller": {"address": "0xe6bb53b3a2e8fc73c0431f9efa51c8dbc4706409"}, "success": true, "count": 1}, {"smartContractMethod": {"name": "reinvest", "signature": "reinvest()", "signatureHash": "fdb5a03e"}, "caller": {"address": "0xef89bf2ab0f4cafd96b8b09423315b4b022ce1be"}, "success": true, "count": 3}, {"smartContractMethod": {"name": "sell", "signature": "sell(uint256)", "signatureHash": "e4849b32"}, "caller": {"address": "0x24992541287d344b3ee610b6ec7f4cde01e8a784"}, "success": true, "count": 1}, {"smartContractMethod": {"name": "sell", "signature": "sell(uint256)", "signatureHash": "e4849b32"}, "caller": {"address": "0x2503425d6f84c32795384e3ee8186d05fdd13ec4"}, "success": true, "count": 1}, {"smartContractMethod": {"name": "sell", "signature": "sell(uint256)", "signatureHash": "e4849b32"}, "caller": {"address": "0x36e058332ae39efad2315776b9c844e30d07388b"}, "success": true, "count": 2}, {"smartContractMethod": {"name": "sell", "signature": "sell(uint256)", "signatureHash": "e4849b32"}, "caller": {"address": "0x409e494dc9d602197af25e201f8b7c3813455a1c"}, "success": false, "count": 1}, {"smartContractMethod": {"name": "sell", "signature": "sell(uint256)", "signatureHash": "e4849b32"}, "caller": {"address": "0x409e494dc9d602197af25e201f8b7c3813455a1c"}, "success": true, "count": 4}, {"smartContractMethod": {"name": "sell", "signature": "sell(uint256)", "signatureHash": "e4849b32"}, "caller": {"address": "0x9acf67684198969687ecadf2d9351981bf6f33b2"}, "success": true, "count": 1}, {"smartContractMethod": {"name": "sell", "signature": "sell(uint256)", "signatureHash": "e4849b32"}, "caller": {"address": "0xe012157d741d568d5f14ddc6bbb724e9132ca86d"}, "success": true, "count": 1}, {"smartContractMethod": {"name": "sell", "signature": "sell(uint256)", "signatureHash": "e4849b32"}, "caller": {"address": "0xe6bb53b3a2e8fc73c0431f9efa51c8dbc4706409"}, "success": true, "count": 2}, {"smartContractMethod": {"name": "sell", "signature": "sell(uint256)", "signatureHash": "e4849b32"}, "caller": {"address": "0xef89bf2ab0f4cafd96b8b09423315b4b022ce1be"}, "success": false, "count": 1}, {"smartContractMethod": {"name": "sell", "signature": "sell(uint256)", "signatureHash": "e4849b32"}, "caller": {"address": "0xef89bf2ab0f4cafd96b8b09423315b4b022ce1be"}, "success": true, "count": 5}, {"smartContractMethod": {"name": "setName", "signature": "setName(string)", "signatureHash": "c47f0027"}, "caller": {"address": "0x984ebf6a71a946facc40f4bcbdfa50ac8edc3fbf"}, "success": false, "count": 1}, {"smartContractMethod": {"name": "setStakingRequirement", "signature": "setStakingRequirement(uint256)", "signatureHash": "8328b610"}, "caller": {"address": "0x9acf67684198969687ecadf2d9351981bf6f33b2"}, "success": true, "count": 1}, {"smartContractMethod": {"name": "withdraw", "signature": "withdraw()", "signatureHash": "3ccfd60b"}, "caller": {"address": "0x24992541287d344b3ee610b6ec7f4cde01e8a784"}, "success": true, "count": 1}, {"smartContractMethod": {"name": "withdraw", "signature": "withdraw()", "signatureHash": "3ccfd60b"}, "caller": {"address": "0x2503425d6f84c32795384e3ee8186d05fdd13ec4"}, "success": true, "count": 1}, {"smartContractMethod": {"name": "withdraw", "signature": "withdraw()", "signatureHash": "3ccfd60b"}, "caller": {"address": "0x36e058332ae39efad2315776b9c844e30d07388b"}, "success": true, "count": 2}, {"smartContractMethod": {"name": "withdraw", "signature": "withdraw()", "signatureHash": "3ccfd60b"}, "caller": {"address": "0x409e494dc9d602197af25e201f8b7c3813455a1c"}, "success": true, "count": 1}, {"smartContractMethod": {"name": "withdraw", "signature": "withdraw()", "signatureHash": "3ccfd60b"}, "caller": {"address": "0x5c25a5bf9478b6c20a9da2117433400a490bf304"}, "success": false, "count": 1}, {"smartContractMethod": {"name": "withdraw", "signature": "withdraw()", "signatureHash": "3ccfd60b"}, "caller": {"address": "0x5c25a5bf9478b6c20a9da2117433400a490bf304"}, "success": true, "count": 1}, {"smartContractMethod": {"name": "withdraw", "signature": "withdraw()", "signatureHash": "3ccfd60b"}, "caller": {"address": "0x8a532865fad20c9009663b81b63e9295ea638a0c"}, "success": true, "count": 1}, {"smartContractMethod": {"name": "withdraw", "signature": "withdraw()", "signatureHash": "3ccfd60b"}, "caller": {"address": "0x980c11c00e51a1e49482d59cb59a3f575ae00268"}, "success": true, "count": 1}, {"smartContractMethod": {"name": "withdraw", "signature": "withdraw()", "signatureHash": "3ccfd60b"}, "caller": {"address": "0x9acf67684198969687ecadf2d9351981bf6f33b2"}, "success": true, "count": 1}, {"smartContractMethod": {"name": "withdraw", "signature": "withdraw()", "signatureHash": "3ccfd60b"}, "caller": {"address": "0xb74d5f0a81ce99ac1857133e489bc2b4954935ff"}, "success": true, "count": 1}, {"smartContractMethod": {"name": "withdraw", "signature": "withdraw()", "signatureHash": "3ccfd60b"}, "caller": {"address": "0xe012157d741d568d5f14ddc6bbb724e9132ca86d"}, "success": true, "count": 1}, {"smartContractMethod": {"name": "withdraw", "signature": "withdraw()", "signatureHash": "3ccfd60b"}, "caller": {"address": "0xe6bb53b3a2e8fc73c0431f9efa51c8dbc4706409"}, "success": true, "count": 1}, {"smartContractMethod": {"name": "withdraw", "signature": "withdraw()", "signatureHash": "3ccfd60b"}, "caller": {"address": "0xef89bf2ab0f4cafd96b8b09423315b4b022ce1be"}, "success": true, "count": 1}]}}}